README.md
cosmosid/__init__.py
cosmosid/api/__init__.py
cosmosid/api/analysis.py
cosmosid/api/artifacts.py
cosmosid/api/auth.py
cosmosid/api/comparative_analyses.py
cosmosid/api/download.py
cosmosid/api/files.py
cosmosid/api/import_workflow.py
cosmosid/api/reports.py
cosmosid/api/upload.py
cosmosid/api/urls.py
cosmosid/api/workflow.py
cosmosid/cli.py
cosmosid/client.py
cosmosid/commands/__init__.py
cosmosid/commands/analysis.py
cosmosid/commands/artifacts.py
cosmosid/commands/comparative_analyses.py
cosmosid/commands/comparative_analyses_export.py
cosmosid/commands/comparatives.py
cosmosid/commands/downloads.py
cosmosid/commands/files.py
cosmosid/commands/mkdir.py
cosmosid/commands/reports.py
cosmosid/commands/runs.py
cosmosid/commands/upload.py
cosmosid/commands/workflows.py
cosmosid/config.py
cosmosid/enums.py
cosmosid/helpers/__init__.py
cosmosid/helpers/argument_actions.py
cosmosid/helpers/argument_validators.py
cosmosid/helpers/auth.py
cosmosid/helpers/downloader.py
cosmosid/helpers/exceptions.py
cosmosid/helpers/parser_builders.py
cosmosid/helpers/thread_logger.py
cosmosid/logger_config.yaml
cosmosid/utils.py
cosmosid_cli-2.1.19.dist-info/LICENSE.txt
cosmosid_cli-2.1.19.dist-info/METADATA
cosmosid_cli-2.1.19.dist-info/WHEEL
cosmosid_cli-2.1.19.dist-info/entry_points.txt
cosmosid_cli-2.1.19.dist-info/RECORD
