Metadata-Version: 2.1
Name: cosmosid_cli
Version: 2.1.19
Summary: Command line interface (CLI) and Python 3 client library for interacting with the CosmosID API
Home-page: https://www.cosmosid.com
License: MIT
Keywords: cosmosID,cosmosid_cli,cosmosid-cli,cosmos
Author: CosmosID
Author-email: support@cosmosid.com
Requires-Python: >=3.6.2,<4
Classifier: Environment :: Console
Classifier: License :: OSI Approved :: MIT License
Classifier: Programming Language :: Python :: 3
Classifier: Programming Language :: Python :: 3.7
Classifier: Programming Language :: Python :: 3.8
Classifier: Programming Language :: Python :: 3.9
Classifier: Programming Language :: Python :: 3.10
Classifier: Programming Language :: Python :: 3.11
Classifier: Programming Language :: Python :: 3.12
Provides-Extra: pycurl
Requires-Dist: cliff (>=3.10.1)
Requires-Dist: concurrent-log-handler (>=0.9.20,<0.10.0)
Requires-Dist: importlib_metadata (>=4.8.3,<5.0.0)
Requires-Dist: pycurl (>=7.45.1,<8.0.0) ; extra == "pycurl"
Requires-Dist: requests (>=2.27.1)
Project-URL: Bug Tracker, https://github.com/CosmosID/cosmosid-cli/issues
Project-URL: Changelog, https://github.com/CosmosID/cosmosid-cli/blob/master/CHANGELOG.md
Project-URL: Documentation, https://docs.cosmosid.com
Project-URL: Repository, https://github.com/CosmosID/cosmosid-cli
